pyfst/__init__.py
pyfst/fst.py
py_r_fst-0.1.1.dist-info/LICENSE
py_r_fst-0.1.1.dist-info/METADATA
py_r_fst-0.1.1.dist-info/WHEEL
py_r_fst-0.1.1.dist-info/top_level.txt
py_r_fst-0.1.1.dist-info/RECORD
