Metadata-Version: 2.2
Name: py-r-fst
Version: 0.1.1
Summary: Python wrapper for the R fst package
Home-page: https://github.com/msdavid/py-r-fst
Author: msdavid
Author-email: msdavid <mauro@sauco.net>
License: Apache 2.0
Project-URL: Homepage, https://github.com/msdavid/py-r-fst
Project-URL: Bug Tracker, https://github.com/msdavid/py-r-fst/issues
Classifier: Programming Language :: Python :: 3
Classifier: License :: OSI Approved :: Apache Software License
Classifier: Operating System :: OS Independent
Requires-Python: >=3.6
License-File: LICENSE
Requires-Dist: pandas>=1.0.0
Requires-Dist: rpy2>=3.4.0
Dynamic: author
Dynamic: home-page
Dynamic: requires-python
